__init__.py
audio/__init__.py
audio/audio_utils.py
audio/export_audio.py
audio/isolate.py
audio/overlap.py
audio/refine_audio.py
audio/voice_detection.py
text/__init__.py
text/create_dataset.py
text/ctc.py
text/ctc_utils.py
text/normalization_helpers.py
text/normalize_text.py
text/process_text.py
text/segment.py
text/split_audio.py
text/text_utils.py
text/transcribe.py
VocalForge-0.1.1.dist-info/LICENSE.md
VocalForge-0.1.1.dist-info/METADATA
VocalForge-0.1.1.dist-info/WHEEL
VocalForge-0.1.1.dist-info/top_level.txt
VocalForge-0.1.1.dist-info/RECORD
