Metadata-Version: 2.1
Name: VocalForge
Version: 0.1.1
Summary: Your one-stop solution for voice dataset creation
Author-email: rio@rioharper.com
Classifier: License :: OSI Approved :: MIT License
Classifier: Environment :: GPU :: NVIDIA CUDA :: 11.3
Requires-Python: >=3.8
License-File: LICENSE.md
Requires-Dist: joblib (==1.2.0)
Requires-Dist: natsort (==8.2.0)
Requires-Dist: numpy (==1.23.2)
Requires-Dist: pydub
Requires-Dist: pandas (==1.4.3)
Requires-Dist: regex (==2022.10.31)
Requires-Dist: scipy (==1.10.1)
Requires-Dist: tqdm (==4.64.1)
Provides-Extra: audio
Requires-Dist: deepfilternet ; extra == 'audio'
Requires-Dist: pyannote.core ; extra == 'audio'
Requires-Dist: pyannote.audio ; extra == 'audio'
Requires-Dist: yt-dlp ; extra == 'audio'
Provides-Extra: text
Requires-Dist: ctc-segmentation ; extra == 'text'
Requires-Dist: nemo (==4.5.5) ; extra == 'text'
Requires-Dist: nemo-text-processing ; extra == 'text'
Requires-Dist: nemo-toolkit ; extra == 'text'
Requires-Dist: num2words (==0.5.12) ; extra == 'text'
Requires-Dist: openai-whisper ; extra == 'text'
Requires-Dist: whisper ; extra == 'text'
